{
  "updated": "2026-01-07T13:45:36.175392+00:00",
  "items": [
    {
      "ItemName": "Onyx bolts",
      "CurrentPrice": 8630,
      "BuyLimit": 11000,
      "FiveMinMean": 8599,
      "HourlyMean": 8592,
      "DailyMean": 8567,
      "WeeklyMean": 8554,
      "MonthlyMean": 8524,
      "BullishConfluence": 5,
      "BearishConfluence": 0,
      "SignalStrength": "STRONG_BULLISH",
      "VolumeConfirmation": "VOLUME_CONFIRMED",
      "PotentialProfit": 9493000.0
    },
    {
      "ItemName": "Green dragon leather",
      "CurrentPrice": 1379,
      "BuyLimit": 13000,
      "FiveMinMean": 1378,
      "HourlyMean": 1375,
      "DailyMean": 1366,
      "WeeklyMean": 1364,
      "MonthlyMean": 1354,
      "BullishConfluence": 5,
      "BearishConfluence": 0,
      "SignalStrength": "STRONG_BULLISH",
      "VolumeConfirmation": "VOLUME_SUPPORTED",
      "PotentialProfit": 1792700.0
    },
    {
      "ItemName": "Super combat potion(2)",
      "CurrentPrice": 8851,
      "BuyLimit": 2000,
      "FiveMinMean": 8754,
      "HourlyMean": 8715,
      "DailyMean": 8480,
      "WeeklyMean": 8426,
      "MonthlyMean": 7488,
      "BullishConfluence": 5,
      "BearishConfluence": 0,
      "SignalStrength": "STRONG_BULLISH",
      "VolumeConfirmation": "WEAK_VOLUME",
      "PotentialProfit": 1770200.0
    },
    {
      "ItemName": "Super defence(3)",
      "CurrentPrice": 3442,
      "BuyLimit": 2000,
      "FiveMinMean": 3385,
      "HourlyMean": 3379,
      "DailyMean": 3377,
      "WeeklyMean": 3264,
      "MonthlyMean": 2867,
      "BullishConfluence": 5,
      "BearishConfluence": 0,
      "SignalStrength": "STRONG_BULLISH",
      "VolumeConfirmation": "VOLUME_CONFIRMED",
      "PotentialProfit": 688400.0
    },
    {
      "ItemName": "Rune javelin tips",
      "CurrentPrice": 562,
      "BuyLimit": 10000,
      "FiveMinMean": 548,
      "HourlyMean": 547,
      "DailyMean": 542,
      "WeeklyMean": 534,
      "MonthlyMean": 521,
      "BullishConfluence": 5,
      "BearishConfluence": 0,
      "SignalStrength": "STRONG_BULLISH",
      "VolumeConfirmation": "VOLUME_CONFIRMED",
      "PotentialProfit": 562000.0
    },
    {
      "ItemName": "Sinister key",
      "CurrentPrice": 24990,
      "BuyLimit": 11000,
      "FiveMinMean": 24984,
      "HourlyMean": 24983,
      "DailyMean": 24982,
      "WeeklyMean": 24916,
      "MonthlyMean": 25013,
      "BullishConfluence": 4,
      "BearishConfluence": 1,
      "SignalStrength": "STRONG_BULLISH",
      "VolumeConfirmation": "WEAK_VOLUME",
      "PotentialProfit": 27489000.0
    },
    {
      "ItemName": "Earth battlestaff",
      "CurrentPrice": 8940,
      "BuyLimit": 18000,
      "FiveMinMean": 8980,
      "HourlyMean": 8979,
      "DailyMean": 8970,
      "WeeklyMean": 8926,
      "MonthlyMean": 8881,
      "BullishConfluence": 4,
      "BearishConfluence": 1,
      "SignalStrength": "STRONG_BULLISH",
      "VolumeConfirmation": "VOLUME_CONFIRMED",
      "PotentialProfit": 16092000.0
    },
    {
      "ItemName": "Air battlestaff",
      "CurrentPrice": 8875,
      "BuyLimit": 18000,
      "FiveMinMean": 8973,
      "HourlyMean": 8971,
      "DailyMean": 8967,
      "WeeklyMean": 8944,
      "MonthlyMean": 8894,
      "BullishConfluence": 4,
      "BearishConfluence": 1,
      "SignalStrength": "STRONG_BULLISH",
      "VolumeConfirmation": "WEAK_VOLUME",
      "PotentialProfit": 15975000.0
    },
    {
      "ItemName": "Bracelet of slaughter",
      "CurrentPrice": 6720,
      "BuyLimit": 15000,
      "FiveMinMean": 6461,
      "HourlyMean": 6461,
      "DailyMean": 6256,
      "WeeklyMean": 5935,
      "MonthlyMean": 5581,
      "BullishConfluence": 4,
      "BearishConfluence": 0,
      "SignalStrength": "STRONG_BULLISH",
      "VolumeConfirmation": "WEAK_VOLUME",
      "PotentialProfit": 10080000.0
    },
    {
      "ItemName": "Snapdragon potion (unf)",
      "CurrentPrice": 8853,
      "BuyLimit": 10000,
      "FiveMinMean": 8773,
      "HourlyMean": 8716,
      "DailyMean": 8583,
      "WeeklyMean": 8827,
      "MonthlyMean": 8762,
      "BullishConfluence": 4,
      "BearishConfluence": 1,
      "SignalStrength": "STRONG_BULLISH",
      "VolumeConfirmation": "WEAK_VOLUME",
      "PotentialProfit": 8853000.0
    },
    {
      "ItemName": "Ruby dragon bolts (e)",
      "CurrentPrice": 3950,
      "BuyLimit": 11000,
      "FiveMinMean": 3943,
      "HourlyMean": 3926,
      "DailyMean": 3931,
      "WeeklyMean": 3875,
      "MonthlyMean": 3705,
      "BullishConfluence": 4,
      "BearishConfluence": 1,
      "SignalStrength": "STRONG_BULLISH",
      "VolumeConfirmation": "WEAK_VOLUME",
      "PotentialProfit": 4345000.0
    },
    {
      "ItemName": "Divine super combat potion(3)",
      "CurrentPrice": 15656,
      "BuyLimit": 2000,
      "FiveMinMean": 15655,
      "HourlyMean": 15653,
      "DailyMean": 15519,
      "WeeklyMean": 15909,
      "MonthlyMean": 14613,
      "BullishConfluence": 4,
      "BearishConfluence": 1,
      "SignalStrength": "STRONG_BULLISH",
      "VolumeConfirmation": "VOLUME_CONFIRMED",
      "PotentialProfit": 3131200.0
    },
    {
      "ItemName": "Xerician fabric",
      "CurrentPrice": 2160,
      "BuyLimit": 13000,
      "FiveMinMean": 2397,
      "HourlyMean": 2389,
      "DailyMean": 2226,
      "WeeklyMean": 2157,
      "MonthlyMean": 1946,
      "BullishConfluence": 4,
      "BearishConfluence": 1,
      "SignalStrength": "STRONG_BULLISH",
      "VolumeConfirmation": "VOLUME_CONFIRMED",
      "PotentialProfit": 2808000.0
    },
    {
      "ItemName": "Amulet of chemistry",
      "CurrentPrice": 1799,
      "BuyLimit": 15000,
      "FiveMinMean": 1799,
      "HourlyMean": 1767,
      "DailyMean": 1638,
      "WeeklyMean": 1408,
      "MonthlyMean": 1392,
      "BullishConfluence": 4,
      "BearishConfluence": 0,
      "SignalStrength": "STRONG_BULLISH",
      "VolumeConfirmation": "WEAK_VOLUME",
      "PotentialProfit": 2698500.0
    },
    {
      "ItemName": "Dragon arrow",
      "CurrentPrice": 1980,
      "BuyLimit": 11000,
      "FiveMinMean": 1995,
      "HourlyMean": 1974,
      "DailyMean": 1971,
      "WeeklyMean": 1934,
      "MonthlyMean": 1895,
      "BullishConfluence": 4,
      "BearishConfluence": 1,
      "SignalStrength": "STRONG_BULLISH",
      "VolumeConfirmation": "WEAK_VOLUME",
      "PotentialProfit": 2178000.0
    },
    {
      "ItemName": "Lava dragon bones",
      "CurrentPrice": 2752,
      "BuyLimit": 7500,
      "FiveMinMean": 2751,
      "HourlyMean": 2751,
      "DailyMean": 2725,
      "WeeklyMean": 2657,
      "MonthlyMean": 2590,
      "BullishConfluence": 4,
      "BearishConfluence": 0,
      "SignalStrength": "STRONG_BULLISH",
      "VolumeConfirmation": "VOLUME_CONFIRMED",
      "PotentialProfit": 2064000.0
    },
    {
      "ItemName": "Dragon arrowtips",
      "CurrentPrice": 1987,
      "BuyLimit": 10000,
      "FiveMinMean": 1921,
      "HourlyMean": 1926,
      "DailyMean": 1919,
      "WeeklyMean": 1908,
      "MonthlyMean": 1858,
      "BullishConfluence": 4,
      "BearishConfluence": 1,
      "SignalStrength": "STRONG_BULLISH",
      "VolumeConfirmation": "WEAK_VOLUME",
      "PotentialProfit": 1987000.0
    },
    {
      "ItemName": "Mahogany repair kit",
      "CurrentPrice": 1196,
      "BuyLimit": 13000,
      "FiveMinMean": 1196,
      "HourlyMean": 1192,
      "DailyMean": 1174,
      "WeeklyMean": 1146,
      "MonthlyMean": 1097,
      "BullishConfluence": 4,
      "BearishConfluence": 0,
      "SignalStrength": "STRONG_BULLISH",
      "VolumeConfirmation": "WEAK_VOLUME",
      "PotentialProfit": 1554800.0
    },
    {
      "ItemName": "Dragon bones",
      "CurrentPrice": 1570,
      "BuyLimit": 7500,
      "FiveMinMean": 1564,
      "HourlyMean": 1567,
      "DailyMean": 1554,
      "WeeklyMean": 1512,
      "MonthlyMean": 1486,
      "BullishConfluence": 4,
      "BearishConfluence": 1,
      "SignalStrength": "STRONG_BULLISH",
      "VolumeConfirmation": "VOLUME_CONFIRMED",
      "PotentialProfit": 1177500.0
    },
    {
      "ItemName": "Wine of zamorak",
      "CurrentPrice": 887,
      "BuyLimit": 11000,
      "FiveMinMean": 885,
      "HourlyMean": 872,
      "DailyMean": 841,
      "WeeklyMean": 849,
      "MonthlyMean": 823,
      "BullishConfluence": 4,
      "BearishConfluence": 1,
      "SignalStrength": "STRONG_BULLISH",
      "VolumeConfirmation": "WEAK_VOLUME",
      "PotentialProfit": 975700.0
    },
    {
      "ItemName": "Camelot teleport (tablet)",
      "CurrentPrice": 621,
      "BuyLimit": 15000,
      "FiveMinMean": 604,
      "HourlyMean": 603,
      "DailyMean": 635,
      "WeeklyMean": 621,
      "MonthlyMean": 558,
      "BullishConfluence": 4,
      "BearishConfluence": 1,
      "SignalStrength": "STRONG_BULLISH",
      "VolumeConfirmation": "WEAK_VOLUME",
      "PotentialProfit": 931500.0
    },
    {
      "ItemName": "Games necklace(8)",
      "CurrentPrice": 723,
      "BuyLimit": 10000,
      "FiveMinMean": 720,
      "HourlyMean": 718,
      "DailyMean": 714,
      "WeeklyMean": 696,
      "MonthlyMean": 729,
      "BullishConfluence": 4,
      "BearishConfluence": 1,
      "SignalStrength": "STRONG_BULLISH",
      "VolumeConfirmation": "VOLUME_CONFIRMED",
      "PotentialProfit": 723000.0
    },
    {
      "ItemName": "Oyster pearls",
      "CurrentPrice": 574,
      "BuyLimit": 11000,
      "FiveMinMean": 601,
      "HourlyMean": 591,
      "DailyMean": 583,
      "WeeklyMean": 577,
      "MonthlyMean": 558,
      "BullishConfluence": 4,
      "BearishConfluence": 1,
      "SignalStrength": "STRONG_BULLISH",
      "VolumeConfirmation": "VOLUME_CONFIRMED",
      "PotentialProfit": 631400.0
    },
    {
      "ItemName": "Aether catalyst",
      "CurrentPrice": 170,
      "BuyLimit": 25000,
      "FiveMinMean": 168,
      "HourlyMean": 167,
      "DailyMean": 164,
      "WeeklyMean": 168,
      "MonthlyMean": 158,
      "BullishConfluence": 4,
      "BearishConfluence": 1,
      "SignalStrength": "STRONG_BULLISH",
      "VolumeConfirmation": "VOLUME_CONFIRMED",
      "PotentialProfit": 425000.0
    },
    {
      "ItemName": "Potato with cheese",
      "CurrentPrice": 303,
      "BuyLimit": 13000,
      "FiveMinMean": 303,
      "HourlyMean": 301,
      "DailyMean": 265,
      "WeeklyMean": 254,
      "MonthlyMean": 185,
      "BullishConfluence": 4,
      "BearishConfluence": 0,
      "SignalStrength": "STRONG_BULLISH",
      "VolumeConfirmation": "WEAK_VOLUME",
      "PotentialProfit": 393900.0
    },
    {
      "ItemName": "Demon tear",
      "CurrentPrice": 281,
      "BuyLimit": 13000,
      "FiveMinMean": 285,
      "HourlyMean": 283,
      "DailyMean": 279,
      "WeeklyMean": 278,
      "MonthlyMean": 224,
      "BullishConfluence": 4,
      "BearishConfluence": 1,
      "SignalStrength": "STRONG_BULLISH",
      "VolumeConfirmation": "WEAK_VOLUME",
      "PotentialProfit": 365300.0
    },
    {
      "ItemName": "Raw swordfish",
      "CurrentPrice": 200,
      "BuyLimit": 15000,
      "FiveMinMean": 196,
      "HourlyMean": 198,
      "DailyMean": 196,
      "WeeklyMean": 195,
      "MonthlyMean": 163,
      "BullishConfluence": 4,
      "BearishConfluence": 1,
      "SignalStrength": "STRONG_BULLISH",
      "VolumeConfirmation": "WEAK_VOLUME",
      "PotentialProfit": 300000.0
    },
    {
      "ItemName": "Charcoal",
      "CurrentPrice": 224,
      "BuyLimit": 13000,
      "FiveMinMean": 206,
      "HourlyMean": 204,
      "DailyMean": 175,
      "WeeklyMean": 176,
      "MonthlyMean": 163,
      "BullishConfluence": 4,
      "BearishConfluence": 1,
      "SignalStrength": "STRONG_BULLISH",
      "VolumeConfirmation": "WEAK_VOLUME",
      "PotentialProfit": 291200.0
    },
    {
      "ItemName": "Yew logs",
      "CurrentPrice": 201,
      "BuyLimit": 12000,
      "FiveMinMean": 202,
      "HourlyMean": 201,
      "DailyMean": 198,
      "WeeklyMean": 186,
      "MonthlyMean": 165,
      "BullishConfluence": 4,
      "BearishConfluence": 1,
      "SignalStrength": "STRONG_BULLISH",
      "VolumeConfirmation": "VOLUME_CONFIRMED",
      "PotentialProfit": 241200.0
    },
    {
      "ItemName": "Rune thrownaxe",
      "CurrentPrice": 207,
      "BuyLimit": 11000,
      "FiveMinMean": 204,
      "HourlyMean": 203,
      "DailyMean": 201,
      "WeeklyMean": 198,
      "MonthlyMean": 207,
      "BullishConfluence": 4,
      "BearishConfluence": 1,
      "SignalStrength": "STRONG_BULLISH",
      "VolumeConfirmation": "WEAK_VOLUME",
      "PotentialProfit": 227700.0
    },
    {
      "ItemName": "Ogre arrow",
      "CurrentPrice": 262,
      "BuyLimit": 7000,
      "FiveMinMean": 263,
      "HourlyMean": 259,
      "DailyMean": 257,
      "WeeklyMean": 241,
      "MonthlyMean": 236,
      "BullishConfluence": 4,
      "BearishConfluence": 1,
      "SignalStrength": "STRONG_BULLISH",
      "VolumeConfirmation": "WEAK_VOLUME",
      "PotentialProfit": 183400.0
    },
    {
      "ItemName": "Red spiders' eggs",
      "CurrentPrice": 139,
      "BuyLimit": 13000,
      "FiveMinMean": 137,
      "HourlyMean": 136,
      "DailyMean": 135,
      "WeeklyMean": 132,
      "MonthlyMean": 148,
      "BullishConfluence": 4,
      "BearishConfluence": 1,
      "SignalStrength": "STRONG_BULLISH",
      "VolumeConfirmation": "WEAK_VOLUME",
      "PotentialProfit": 180700.0
    },
    {
      "ItemName": "Mystic hat",
      "CurrentPrice": 13525,
      "BuyLimit": 125,
      "FiveMinMean": 13049,
      "HourlyMean": 12812,
      "DailyMean": 13101,
      "WeeklyMean": 12898,
      "MonthlyMean": 12235,
      "BullishConfluence": 4,
      "BearishConfluence": 1,
      "SignalStrength": "STRONG_BULLISH",
      "VolumeConfirmation": "VOLUME_CONFIRMED",
      "PotentialProfit": 169063.0
    },
    {
      "ItemName": "Xerician top",
      "CurrentPrice": 11500,
      "BuyLimit": 125,
      "FiveMinMean": 11575,
      "HourlyMean": 11540,
      "DailyMean": 11209,
      "WeeklyMean": 10857,
      "MonthlyMean": 10007,
      "BullishConfluence": 4,
      "BearishConfluence": 1,
      "SignalStrength": "STRONG_BULLISH",
      "VolumeConfirmation": "WEAK_VOLUME",
      "PotentialProfit": 143750.0
    },
    {
      "ItemName": "Raw salmon",
      "CurrentPrice": 84,
      "BuyLimit": 15000,
      "FiveMinMean": 89,
      "HourlyMean": 87,
      "DailyMean": 82,
      "WeeklyMean": 76,
      "MonthlyMean": 68,
      "BullishConfluence": 4,
      "BearishConfluence": 1,
      "SignalStrength": "STRONG_BULLISH",
      "VolumeConfirmation": "WEAK_VOLUME",
      "PotentialProfit": 126000.0
    },
    {
      "ItemName": "Adamant arrowtips",
      "CurrentPrice": 120,
      "BuyLimit": 10000,
      "FiveMinMean": 120,
      "HourlyMean": 115,
      "DailyMean": 111,
      "WeeklyMean": 102,
      "MonthlyMean": 89,
      "BullishConfluence": 4,
      "BearishConfluence": 0,
      "SignalStrength": "STRONG_BULLISH",
      "VolumeConfirmation": "WEAK_VOLUME",
      "PotentialProfit": 120000.0
    },
    {
      "ItemName": "Blue d'hide body",
      "CurrentPrice": 5206,
      "BuyLimit": 125,
      "FiveMinMean": 5118,
      "HourlyMean": 5142,
      "DailyMean": 5138,
      "WeeklyMean": 5026,
      "MonthlyMean": 4926,
      "BullishConfluence": 4,
      "BearishConfluence": 1,
      "SignalStrength": "STRONG_BULLISH",
      "VolumeConfirmation": "WEAK_VOLUME",
      "PotentialProfit": 65075.0
    },
    {
      "ItemName": "Ball of wool",
      "CurrentPrice": 44,
      "BuyLimit": 13000,
      "FiveMinMean": 42,
      "HourlyMean": 43,
      "DailyMean": 42,
      "WeeklyMean": 40,
      "MonthlyMean": 34,
      "BullishConfluence": 4,
      "BearishConfluence": 1,
      "SignalStrength": "STRONG_BULLISH",
      "VolumeConfirmation": "VOLUME_CONFIRMED",
      "PotentialProfit": 57200.0
    },
    {
      "ItemName": "Papaya tree seed",
      "CurrentPrice": 2392,
      "BuyLimit": 200,
      "FiveMinMean": 1813,
      "HourlyMean": 1863,
      "DailyMean": 1809,
      "WeeklyMean": 1774,
      "MonthlyMean": 1765,
      "BullishConfluence": 4,
      "BearishConfluence": 1,
      "SignalStrength": "STRONG_BULLISH",
      "VolumeConfirmation": "VOLUME_CONFIRMED",
      "PotentialProfit": 47840.0
    },
    {
      "ItemName": "Curry leaf",
      "CurrentPrice": 41,
      "BuyLimit": 11000,
      "FiveMinMean": 41,
      "HourlyMean": 40,
      "DailyMean": 35,
      "WeeklyMean": 33,
      "MonthlyMean": 31,
      "BullishConfluence": 4,
      "BearishConfluence": 0,
      "SignalStrength": "STRONG_BULLISH",
      "VolumeConfirmation": "WEAK_VOLUME",
      "PotentialProfit": 45100.0
    },
    {
      "ItemName": "Mithril platebody",
      "CurrentPrice": 2860,
      "BuyLimit": 125,
      "FiveMinMean": 2848,
      "HourlyMean": 2838,
      "DailyMean": 2809,
      "WeeklyMean": 2774,
      "MonthlyMean": 2783,
      "BullishConfluence": 4,
      "BearishConfluence": 1,
      "SignalStrength": "STRONG_BULLISH",
      "VolumeConfirmation": "WEAK_VOLUME",
      "PotentialProfit": 35750.0
    },
    {
      "ItemName": "Adamant chainbody",
      "CurrentPrice": 2633,
      "BuyLimit": 125,
      "FiveMinMean": 2600,
      "HourlyMean": 2632,
      "DailyMean": 2617,
      "WeeklyMean": 2583,
      "MonthlyMean": 2567,
      "BullishConfluence": 4,
      "BearishConfluence": 1,
      "SignalStrength": "STRONG_BULLISH",
      "VolumeConfirmation": "WEAK_VOLUME",
      "PotentialProfit": 32913.0
    },
    {
      "ItemName": "Adamant battleaxe",
      "CurrentPrice": 2222,
      "BuyLimit": 125,
      "FiveMinMean": 2196,
      "HourlyMean": 2254,
      "DailyMean": 2229,
      "WeeklyMean": 2178,
      "MonthlyMean": 2109,
      "BullishConfluence": 4,
      "BearishConfluence": 1,
      "SignalStrength": "STRONG_BULLISH",
      "VolumeConfirmation": "WEAK_VOLUME",
      "PotentialProfit": 27775.0
    },
    {
      "ItemName": "Adamant sq shield",
      "CurrentPrice": 2050,
      "BuyLimit": 125,
      "FiveMinMean": 2048,
      "HourlyMean": 2057,
      "DailyMean": 2048,
      "WeeklyMean": 2041,
      "MonthlyMean": 2027,
      "BullishConfluence": 4,
      "BearishConfluence": 1,
      "SignalStrength": "STRONG_BULLISH",
      "VolumeConfirmation": "WEAK_VOLUME",
      "PotentialProfit": 25625.0
    },
    {
      "ItemName": "Weeds",
      "CurrentPrice": 234,
      "BuyLimit": 600,
      "FiveMinMean": 234,
      "HourlyMean": 233,
      "DailyMean": 231,
      "WeeklyMean": 229,
      "MonthlyMean": 224,
      "BullishConfluence": 4,
      "BearishConfluence": 0,
      "SignalStrength": "STRONG_BULLISH",
      "VolumeConfirmation": "VOLUME_CONFIRMED",
      "PotentialProfit": 14040.0
    },
    {
      "ItemName": "Steel platebody",
      "CurrentPrice": 925,
      "BuyLimit": 125,
      "FiveMinMean": 925,
      "HourlyMean": 920,
      "DailyMean": 901,
      "WeeklyMean": 898,
      "MonthlyMean": 891,
      "BullishConfluence": 4,
      "BearishConfluence": 0,
      "SignalStrength": "STRONG_BULLISH",
      "VolumeConfirmation": "WEAK_VOLUME",
      "PotentialProfit": 11563.0
    },
    {
      "ItemName": "Strength potion(3)",
      "CurrentPrice": 54,
      "BuyLimit": 2000,
      "FiveMinMean": 50,
      "HourlyMean": 50,
      "DailyMean": 47,
      "WeeklyMean": 46,
      "MonthlyMean": 45,
      "BullishConfluence": 4,
      "BearishConfluence": 0,
      "SignalStrength": "STRONG_BULLISH",
      "VolumeConfirmation": "VOLUME_SUPPORTED",
      "PotentialProfit": 10800.0
    },
    {
      "ItemName": "Snakeskin boots",
      "CurrentPrice": 816,
      "BuyLimit": 125,
      "FiveMinMean": 504,
      "HourlyMean": 473,
      "DailyMean": 537,
      "WeeklyMean": 474,
      "MonthlyMean": 468,
      "BullishConfluence": 4,
      "BearishConfluence": 1,
      "SignalStrength": "STRONG_BULLISH",
      "VolumeConfirmation": "WEAK_VOLUME",
      "PotentialProfit": 10200.0
    },
    {
      "ItemName": "Calquat tree seed",
      "CurrentPrice": 448,
      "BuyLimit": 200,
      "FiveMinMean": 300,
      "HourlyMean": 304,
      "DailyMean": 301,
      "WeeklyMean": 279,
      "MonthlyMean": 235,
      "BullishConfluence": 4,
      "BearishConfluence": 1,
      "SignalStrength": "STRONG_BULLISH",
      "VolumeConfirmation": "WEAK_VOLUME",
      "PotentialProfit": 8960.0
    },
    {
      "ItemName": "Lockpick",
      "CurrentPrice": 200,
      "BuyLimit": 250,
      "FiveMinMean": 189,
      "HourlyMean": 250,
      "DailyMean": 215,
      "WeeklyMean": 194,
      "MonthlyMean": 145,
      "BullishConfluence": 4,
      "BearishConfluence": 1,
      "SignalStrength": "STRONG_BULLISH",
      "VolumeConfirmation": "VOLUME_CONFIRMED",
      "PotentialProfit": 5000.0
    }
  ],
  "methodology": "VeryGranular_MultiTimeframeConfluence"
}