{
  "updated": "2026-01-04T09:05:34.849214+00:00",
  "items": [
    {
      "ItemName": "Grimy kwuarm",
      "CurrentPrice": 3663,
      "BuyLimit": 13000,
      "FiveMinMean": 3615,
      "HourlyMean": 3592,
      "DailyMean": 3578,
      "WeeklyMean": 3561,
      "MonthlyMean": 3186,
      "BullishConfluence": 5,
      "BearishConfluence": 0,
      "SignalStrength": "STRONG_BULLISH",
      "VolumeConfirmation": "WEAK_VOLUME",
      "PotentialProfit": 4761900.0
    },
    {
      "ItemName": "Earth impling jar",
      "CurrentPrice": 2446,
      "BuyLimit": 18000,
      "FiveMinMean": 2441,
      "HourlyMean": 2423,
      "DailyMean": 2382,
      "WeeklyMean": 1995,
      "MonthlyMean": 1378,
      "BullishConfluence": 5,
      "BearishConfluence": 0,
      "SignalStrength": "STRONG_BULLISH",
      "VolumeConfirmation": "WEAK_VOLUME",
      "PotentialProfit": 4402800.0
    },
    {
      "ItemName": "Redwood logs",
      "CurrentPrice": 1045,
      "BuyLimit": 12000,
      "FiveMinMean": 1009,
      "HourlyMean": 998,
      "DailyMean": 991,
      "WeeklyMean": 954,
      "MonthlyMean": 859,
      "BullishConfluence": 5,
      "BearishConfluence": 0,
      "SignalStrength": "STRONG_BULLISH",
      "VolumeConfirmation": "VOLUME_CONFIRMED",
      "PotentialProfit": 1254000.0
    },
    {
      "ItemName": "Super defence(4)",
      "CurrentPrice": 4768,
      "BuyLimit": 2000,
      "FiveMinMean": 4656,
      "HourlyMean": 4653,
      "DailyMean": 4634,
      "WeeklyMean": 4367,
      "MonthlyMean": 3901,
      "BullishConfluence": 5,
      "BearishConfluence": 0,
      "SignalStrength": "STRONG_BULLISH",
      "VolumeConfirmation": "VOLUME_SUPPORTED",
      "PotentialProfit": 953600.0
    },
    {
      "ItemName": "Runite bolts (unf)",
      "CurrentPrice": 300,
      "BuyLimit": 13000,
      "FiveMinMean": 298,
      "HourlyMean": 297,
      "DailyMean": 292,
      "WeeklyMean": 276,
      "MonthlyMean": 233,
      "BullishConfluence": 5,
      "BearishConfluence": 0,
      "SignalStrength": "STRONG_BULLISH",
      "VolumeConfirmation": "WEAK_VOLUME",
      "PotentialProfit": 390000.0
    },
    {
      "ItemName": "Green d'hide vambraces",
      "CurrentPrice": 1499,
      "BuyLimit": 125,
      "FiveMinMean": 1428,
      "HourlyMean": 1414,
      "DailyMean": 1319,
      "WeeklyMean": 1295,
      "MonthlyMean": 1283,
      "BullishConfluence": 5,
      "BearishConfluence": 0,
      "SignalStrength": "STRONG_BULLISH",
      "VolumeConfirmation": "VOLUME_SUPPORTED",
      "PotentialProfit": 18738.0
    },
    {
      "ItemName": "Infinity gloves",
      "CurrentPrice": 1750857,
      "BuyLimit": 125,
      "FiveMinMean": 1750515,
      "HourlyMean": 1749914,
      "DailyMean": 1865425,
      "WeeklyMean": 1726284,
      "MonthlyMean": 1141196,
      "BullishConfluence": 4,
      "BearishConfluence": 1,
      "SignalStrength": "STRONG_BULLISH",
      "VolumeConfirmation": "WEAK_VOLUME",
      "PotentialProfit": 21885713.0
    },
    {
      "ItemName": "Infinity top",
      "CurrentPrice": 1748138,
      "BuyLimit": 125,
      "FiveMinMean": 1741982,
      "HourlyMean": 1752137,
      "DailyMean": 1620814,
      "WeeklyMean": 1426493,
      "MonthlyMean": 1311453,
      "BullishConfluence": 4,
      "BearishConfluence": 1,
      "SignalStrength": "STRONG_BULLISH",
      "VolumeConfirmation": "WEAK_VOLUME",
      "PotentialProfit": 21851725.0
    },
    {
      "ItemName": "Earth battlestaff",
      "CurrentPrice": 8960,
      "BuyLimit": 18000,
      "FiveMinMean": 8973,
      "HourlyMean": 8919,
      "DailyMean": 8915,
      "WeeklyMean": 8914,
      "MonthlyMean": 8882,
      "BullishConfluence": 4,
      "BearishConfluence": 1,
      "SignalStrength": "STRONG_BULLISH",
      "VolumeConfirmation": "WEAK_VOLUME",
      "PotentialProfit": 16128000.0
    },
    {
      "ItemName": "Uncut dragonstone",
      "CurrentPrice": 15538,
      "BuyLimit": 10000,
      "FiveMinMean": 15547,
      "HourlyMean": 15466,
      "DailyMean": 15088,
      "WeeklyMean": 14337,
      "MonthlyMean": 14057,
      "BullishConfluence": 4,
      "BearishConfluence": 1,
      "SignalStrength": "STRONG_BULLISH",
      "VolumeConfirmation": "WEAK_VOLUME",
      "PotentialProfit": 15538000.0
    },
    {
      "ItemName": "Combat bracelet",
      "CurrentPrice": 12290,
      "BuyLimit": 10000,
      "FiveMinMean": 12281,
      "HourlyMean": 12281,
      "DailyMean": 12271,
      "WeeklyMean": 12250,
      "MonthlyMean": 12236,
      "BullishConfluence": 4,
      "BearishConfluence": 0,
      "SignalStrength": "STRONG_BULLISH",
      "VolumeConfirmation": "WEAK_VOLUME",
      "PotentialProfit": 12290000.0
    },
    {
      "ItemName": "Skills necklace(4)",
      "CurrentPrice": 12000,
      "BuyLimit": 10000,
      "FiveMinMean": 12128,
      "HourlyMean": 11939,
      "DailyMean": 11904,
      "WeeklyMean": 11838,
      "MonthlyMean": 11800,
      "BullishConfluence": 4,
      "BearishConfluence": 1,
      "SignalStrength": "STRONG_BULLISH",
      "VolumeConfirmation": "VOLUME_SUPPORTED",
      "PotentialProfit": 12000000.0
    },
    {
      "ItemName": "Burning amulet(5)",
      "CurrentPrice": 6235,
      "BuyLimit": 10000,
      "FiveMinMean": 6162,
      "HourlyMean": 6097,
      "DailyMean": 6089,
      "WeeklyMean": 6059,
      "MonthlyMean": 6390,
      "BullishConfluence": 4,
      "BearishConfluence": 1,
      "SignalStrength": "STRONG_BULLISH",
      "VolumeConfirmation": "VOLUME_CONFIRMED",
      "PotentialProfit": 6235000.0
    },
    {
      "ItemName": "Torstol",
      "CurrentPrice": 4170,
      "BuyLimit": 11000,
      "FiveMinMean": 4149,
      "HourlyMean": 4162,
      "DailyMean": 4130,
      "WeeklyMean": 3991,
      "MonthlyMean": 3667,
      "BullishConfluence": 4,
      "BearishConfluence": 1,
      "SignalStrength": "STRONG_BULLISH",
      "VolumeConfirmation": "WEAK_VOLUME",
      "PotentialProfit": 4587000.0
    },
    {
      "ItemName": "Runite ore",
      "CurrentPrice": 10070,
      "BuyLimit": 4500,
      "FiveMinMean": 10099,
      "HourlyMean": 10092,
      "DailyMean": 10076,
      "WeeklyMean": 10032,
      "MonthlyMean": 9875,
      "BullishConfluence": 4,
      "BearishConfluence": 1,
      "SignalStrength": "STRONG_BULLISH",
      "VolumeConfirmation": "WEAK_VOLUME",
      "PotentialProfit": 4531500.0
    },
    {
      "ItemName": "Diamond dragon bolts (e)",
      "CurrentPrice": 4001,
      "BuyLimit": 11000,
      "FiveMinMean": 4040,
      "HourlyMean": 3981,
      "DailyMean": 3906,
      "WeeklyMean": 3832,
      "MonthlyMean": 3606,
      "BullishConfluence": 4,
      "BearishConfluence": 1,
      "SignalStrength": "STRONG_BULLISH",
      "VolumeConfirmation": "VOLUME_SUPPORTED",
      "PotentialProfit": 4401100.0
    },
    {
      "ItemName": "Ruby dragon bolts (e)",
      "CurrentPrice": 3944,
      "BuyLimit": 11000,
      "FiveMinMean": 3897,
      "HourlyMean": 3864,
      "DailyMean": 3854,
      "WeeklyMean": 3929,
      "MonthlyMean": 3673,
      "BullishConfluence": 4,
      "BearishConfluence": 1,
      "SignalStrength": "STRONG_BULLISH",
      "VolumeConfirmation": "WEAK_VOLUME",
      "PotentialProfit": 4338400.0
    },
    {
      "ItemName": "Urium remains",
      "CurrentPrice": 5740,
      "BuyLimit": 7500,
      "FiveMinMean": 5740,
      "HourlyMean": 5739,
      "DailyMean": 5737,
      "WeeklyMean": 5663,
      "MonthlyMean": 5394,
      "BullishConfluence": 4,
      "BearishConfluence": 0,
      "SignalStrength": "STRONG_BULLISH",
      "VolumeConfirmation": "VOLUME_CONFIRMED",
      "PotentialProfit": 4305000.0
    },
    {
      "ItemName": "Grimy cadantine",
      "CurrentPrice": 3731,
      "BuyLimit": 11000,
      "FiveMinMean": 3459,
      "HourlyMean": 3397,
      "DailyMean": 3411,
      "WeeklyMean": 3097,
      "MonthlyMean": 2766,
      "BullishConfluence": 4,
      "BearishConfluence": 1,
      "SignalStrength": "STRONG_BULLISH",
      "VolumeConfirmation": "WEAK_VOLUME",
      "PotentialProfit": 4104100.0
    },
    {
      "ItemName": "Dwarf weed",
      "CurrentPrice": 3344,
      "BuyLimit": 11000,
      "FiveMinMean": 3326,
      "HourlyMean": 3301,
      "DailyMean": 3390,
      "WeeklyMean": 3386,
      "MonthlyMean": 2833,
      "BullishConfluence": 4,
      "BearishConfluence": 1,
      "SignalStrength": "STRONG_BULLISH",
      "VolumeConfirmation": "WEAK_VOLUME",
      "PotentialProfit": 3678400.0
    },
    {
      "ItemName": "Dwarf weed potion (unf)",
      "CurrentPrice": 3580,
      "BuyLimit": 10000,
      "FiveMinMean": 3577,
      "HourlyMean": 3576,
      "DailyMean": 3619,
      "WeeklyMean": 3603,
      "MonthlyMean": 3066,
      "BullishConfluence": 4,
      "BearishConfluence": 1,
      "SignalStrength": "STRONG_BULLISH",
      "VolumeConfirmation": "VOLUME_CONFIRMED",
      "PotentialProfit": 3580000.0
    },
    {
      "ItemName": "Super combat potion(4)",
      "CurrentPrice": 17247,
      "BuyLimit": 2000,
      "FiveMinMean": 17027,
      "HourlyMean": 17180,
      "DailyMean": 16930,
      "WeeklyMean": 16791,
      "MonthlyMean": 15309,
      "BullishConfluence": 4,
      "BearishConfluence": 1,
      "SignalStrength": "STRONG_BULLISH",
      "VolumeConfirmation": "VOLUME_CONFIRMED",
      "PotentialProfit": 3449400.0
    },
    {
      "ItemName": "Black dragon leather",
      "CurrentPrice": 3133,
      "BuyLimit": 11000,
      "FiveMinMean": 3120,
      "HourlyMean": 3133,
      "DailyMean": 3099,
      "WeeklyMean": 2997,
      "MonthlyMean": 2925,
      "BullishConfluence": 4,
      "BearishConfluence": 1,
      "SignalStrength": "STRONG_BULLISH",
      "VolumeConfirmation": "VOLUME_CONFIRMED",
      "PotentialProfit": 3446300.0
    },
    {
      "ItemName": "Dragonfruit tree seed",
      "CurrentPrice": 147900,
      "BuyLimit": 200,
      "FiveMinMean": 147105,
      "HourlyMean": 147076,
      "DailyMean": 146969,
      "WeeklyMean": 144950,
      "MonthlyMean": 153575,
      "BullishConfluence": 4,
      "BearishConfluence": 1,
      "SignalStrength": "STRONG_BULLISH",
      "VolumeConfirmation": "VOLUME_SUPPORTED",
      "PotentialProfit": 2958000.0
    },
    {
      "ItemName": "Lily of the sands",
      "CurrentPrice": 2195,
      "BuyLimit": 13000,
      "FiveMinMean": 2193,
      "HourlyMean": 2193,
      "DailyMean": 2187,
      "WeeklyMean": 2180,
      "MonthlyMean": 1928,
      "BullishConfluence": 4,
      "BearishConfluence": 0,
      "SignalStrength": "STRONG_BULLISH",
      "VolumeConfirmation": "VOLUME_SUPPORTED",
      "PotentialProfit": 2853500.0
    },
    {
      "ItemName": "Annakarl teleport (tablet)",
      "CurrentPrice": 2450,
      "BuyLimit": 10000,
      "FiveMinMean": 2577,
      "HourlyMean": 2568,
      "DailyMean": 2518,
      "WeeklyMean": 2490,
      "MonthlyMean": 2088,
      "BullishConfluence": 4,
      "BearishConfluence": 1,
      "SignalStrength": "STRONG_BULLISH",
      "VolumeConfirmation": "VOLUME_SUPPORTED",
      "PotentialProfit": 2450000.0
    },
    {
      "ItemName": "Green dragon leather",
      "CurrentPrice": 1394,
      "BuyLimit": 13000,
      "FiveMinMean": 1389,
      "HourlyMean": 1378,
      "DailyMean": 1381,
      "WeeklyMean": 1362,
      "MonthlyMean": 1354,
      "BullishConfluence": 4,
      "BearishConfluence": 1,
      "SignalStrength": "STRONG_BULLISH",
      "VolumeConfirmation": "VOLUME_CONFIRMED",
      "PotentialProfit": 1812200.0
    },
    {
      "ItemName": "Tuna potato",
      "CurrentPrice": 1276,
      "BuyLimit": 13000,
      "FiveMinMean": 1227,
      "HourlyMean": 1232,
      "DailyMean": 1219,
      "WeeklyMean": 1195,
      "MonthlyMean": 1058,
      "BullishConfluence": 4,
      "BearishConfluence": 1,
      "SignalStrength": "STRONG_BULLISH",
      "VolumeConfirmation": "VOLUME_SUPPORTED",
      "PotentialProfit": 1658800.0
    },
    {
      "ItemName": "Dynamite",
      "CurrentPrice": 1203,
      "BuyLimit": 13000,
      "FiveMinMean": 1219,
      "HourlyMean": 1217,
      "DailyMean": 1127,
      "WeeklyMean": 970,
      "MonthlyMean": 896,
      "BullishConfluence": 4,
      "BearishConfluence": 1,
      "SignalStrength": "STRONG_BULLISH",
      "VolumeConfirmation": "VOLUME_CONFIRMED",
      "PotentialProfit": 1563900.0
    },
    {
      "ItemName": "Zogre bones",
      "CurrentPrice": 5002,
      "BuyLimit": 3000,
      "FiveMinMean": 4444,
      "HourlyMean": 3709,
      "DailyMean": 35929,
      "WeeklyMean": 4903,
      "MonthlyMean": 1249,
      "BullishConfluence": 4,
      "BearishConfluence": 1,
      "SignalStrength": "STRONG_BULLISH",
      "VolumeConfirmation": "VOLUME_CONFIRMED",
      "PotentialProfit": 1500600.0
    },
    {
      "ItemName": "Divine ranging potion(4)",
      "CurrentPrice": 6591,
      "BuyLimit": 2000,
      "FiveMinMean": 6516,
      "HourlyMean": 6608,
      "DailyMean": 6544,
      "WeeklyMean": 6425,
      "MonthlyMean": 5507,
      "BullishConfluence": 4,
      "BearishConfluence": 1,
      "SignalStrength": "STRONG_BULLISH",
      "VolumeConfirmation": "WEAK_VOLUME",
      "PotentialProfit": 1318200.0
    },
    {
      "ItemName": "Wyvern bones",
      "CurrentPrice": 1475,
      "BuyLimit": 7500,
      "FiveMinMean": 1464,
      "HourlyMean": 1462,
      "DailyMean": 1502,
      "WeeklyMean": 1469,
      "MonthlyMean": 1468,
      "BullishConfluence": 4,
      "BearishConfluence": 1,
      "SignalStrength": "STRONG_BULLISH",
      "VolumeConfirmation": "WEAK_VOLUME",
      "PotentialProfit": 1106250.0
    },
    {
      "ItemName": "Super strength(4)",
      "CurrentPrice": 5492,
      "BuyLimit": 2000,
      "FiveMinMean": 5450,
      "HourlyMean": 5368,
      "DailyMean": 5480,
      "WeeklyMean": 5462,
      "MonthlyMean": 4682,
      "BullishConfluence": 4,
      "BearishConfluence": 1,
      "SignalStrength": "STRONG_BULLISH",
      "VolumeConfirmation": "WEAK_VOLUME",
      "PotentialProfit": 1098400.0
    },
    {
      "ItemName": "Mystic robe top",
      "CurrentPrice": 71249,
      "BuyLimit": 125,
      "FiveMinMean": 71539,
      "HourlyMean": 71450,
      "DailyMean": 71403,
      "WeeklyMean": 71367,
      "MonthlyMean": 71229,
      "BullishConfluence": 4,
      "BearishConfluence": 1,
      "SignalStrength": "STRONG_BULLISH",
      "VolumeConfirmation": "WEAK_VOLUME",
      "PotentialProfit": 890613.0
    },
    {
      "ItemName": "Super strength(3)",
      "CurrentPrice": 4035,
      "BuyLimit": 2000,
      "FiveMinMean": 4025,
      "HourlyMean": 4030,
      "DailyMean": 4013,
      "WeeklyMean": 3973,
      "MonthlyMean": 3373,
      "BullishConfluence": 4,
      "BearishConfluence": 1,
      "SignalStrength": "STRONG_BULLISH",
      "VolumeConfirmation": "WEAK_VOLUME",
      "PotentialProfit": 807000.0
    },
    {
      "ItemName": "Binding necklace",
      "CurrentPrice": 794,
      "BuyLimit": 10000,
      "FiveMinMean": 793,
      "HourlyMean": 782,
      "DailyMean": 771,
      "WeeklyMean": 772,
      "MonthlyMean": 760,
      "BullishConfluence": 4,
      "BearishConfluence": 1,
      "SignalStrength": "STRONG_BULLISH",
      "VolumeConfirmation": "WEAK_VOLUME",
      "PotentialProfit": 794000.0
    },
    {
      "ItemName": "Huasca seed",
      "CurrentPrice": 39400,
      "BuyLimit": 200,
      "FiveMinMean": 39677,
      "HourlyMean": 39628,
      "DailyMean": 39319,
      "WeeklyMean": 38719,
      "MonthlyMean": 38066,
      "BullishConfluence": 4,
      "BearishConfluence": 1,
      "SignalStrength": "STRONG_BULLISH",
      "VolumeConfirmation": "VOLUME_SUPPORTED",
      "PotentialProfit": 788000.0
    },
    {
      "ItemName": "Raw shark",
      "CurrentPrice": 508,
      "BuyLimit": 15000,
      "FiveMinMean": 510,
      "HourlyMean": 509,
      "DailyMean": 505,
      "WeeklyMean": 483,
      "MonthlyMean": 415,
      "BullishConfluence": 4,
      "BearishConfluence": 1,
      "SignalStrength": "STRONG_BULLISH",
      "VolumeConfirmation": "WEAK_VOLUME",
      "PotentialProfit": 762000.0
    },
    {
      "ItemName": "Raw karambwan",
      "CurrentPrice": 569,
      "BuyLimit": 13000,
      "FiveMinMean": 567,
      "HourlyMean": 558,
      "DailyMean": 573,
      "WeeklyMean": 560,
      "MonthlyMean": 476,
      "BullishConfluence": 4,
      "BearishConfluence": 1,
      "SignalStrength": "STRONG_BULLISH",
      "VolumeConfirmation": "VOLUME_SUPPORTED",
      "PotentialProfit": 739700.0
    },
    {
      "ItemName": "Super defence(3)",
      "CurrentPrice": 3301,
      "BuyLimit": 2000,
      "FiveMinMean": 3300,
      "HourlyMean": 3365,
      "DailyMean": 3325,
      "WeeklyMean": 3164,
      "MonthlyMean": 2812,
      "BullishConfluence": 4,
      "BearishConfluence": 1,
      "SignalStrength": "STRONG_BULLISH",
      "VolumeConfirmation": "VOLUME_SUPPORTED",
      "PotentialProfit": 660200.0
    },
    {
      "ItemName": "Mystic robe bottom",
      "CurrentPrice": 47222,
      "BuyLimit": 125,
      "FiveMinMean": 47465,
      "HourlyMean": 47422,
      "DailyMean": 47392,
      "WeeklyMean": 47341,
      "MonthlyMean": 47173,
      "BullishConfluence": 4,
      "BearishConfluence": 1,
      "SignalStrength": "STRONG_BULLISH",
      "VolumeConfirmation": "WEAK_VOLUME",
      "PotentialProfit": 590275.0
    },
    {
      "ItemName": "Snape grass",
      "CurrentPrice": 428,
      "BuyLimit": 13000,
      "FiveMinMean": 421,
      "HourlyMean": 416,
      "DailyMean": 398,
      "WeeklyMean": 400,
      "MonthlyMean": 376,
      "BullishConfluence": 4,
      "BearishConfluence": 1,
      "SignalStrength": "STRONG_BULLISH",
      "VolumeConfirmation": "VOLUME_SUPPORTED",
      "PotentialProfit": 556400.0
    },
    {
      "ItemName": "Super attack(4)",
      "CurrentPrice": 2761,
      "BuyLimit": 2000,
      "FiveMinMean": 2784,
      "HourlyMean": 2770,
      "DailyMean": 2709,
      "WeeklyMean": 2499,
      "MonthlyMean": 2461,
      "BullishConfluence": 4,
      "BearishConfluence": 1,
      "SignalStrength": "STRONG_BULLISH",
      "VolumeConfirmation": "WEAK_VOLUME",
      "PotentialProfit": 552200.0
    },
    {
      "ItemName": "Papyrus",
      "CurrentPrice": 300,
      "BuyLimit": 13000,
      "FiveMinMean": 162,
      "HourlyMean": 208,
      "DailyMean": 174,
      "WeeklyMean": 74,
      "MonthlyMean": 29,
      "BullishConfluence": 4,
      "BearishConfluence": 1,
      "SignalStrength": "STRONG_BULLISH",
      "VolumeConfirmation": "WEAK_VOLUME",
      "PotentialProfit": 390000.0
    },
    {
      "ItemName": "Leather",
      "CurrentPrice": 299,
      "BuyLimit": 13000,
      "FiveMinMean": 283,
      "HourlyMean": 272,
      "DailyMean": 265,
      "WeeklyMean": 266,
      "MonthlyMean": 264,
      "BullishConfluence": 4,
      "BearishConfluence": 1,
      "SignalStrength": "STRONG_BULLISH",
      "VolumeConfirmation": "VOLUME_SUPPORTED",
      "PotentialProfit": 388700.0
    },
    {
      "ItemName": "Super attack(3)",
      "CurrentPrice": 1941,
      "BuyLimit": 2000,
      "FiveMinMean": 1950,
      "HourlyMean": 1938,
      "DailyMean": 1901,
      "WeeklyMean": 1763,
      "MonthlyMean": 1733,
      "BullishConfluence": 4,
      "BearishConfluence": 1,
      "SignalStrength": "STRONG_BULLISH",
      "VolumeConfirmation": "VOLUME_CONFIRMED",
      "PotentialProfit": 388200.0
    },
    {
      "ItemName": "Yew longbow (u)",
      "CurrentPrice": 335,
      "BuyLimit": 10000,
      "FiveMinMean": 329,
      "HourlyMean": 325,
      "DailyMean": 318,
      "WeeklyMean": 303,
      "MonthlyMean": 306,
      "BullishConfluence": 4,
      "BearishConfluence": 1,
      "SignalStrength": "STRONG_BULLISH",
      "VolumeConfirmation": "VOLUME_CONFIRMED",
      "PotentialProfit": 335000.0
    },
    {
      "ItemName": "Runite bolts",
      "CurrentPrice": 255,
      "BuyLimit": 11000,
      "FiveMinMean": 254,
      "HourlyMean": 252,
      "DailyMean": 261,
      "WeeklyMean": 253,
      "MonthlyMean": 220,
      "BullishConfluence": 4,
      "BearishConfluence": 1,
      "SignalStrength": "STRONG_BULLISH",
      "VolumeConfirmation": "WEAK_VOLUME",
      "PotentialProfit": 280500.0
    },
    {
      "ItemName": "Mahogany logs",
      "CurrentPrice": 251,
      "BuyLimit": 11000,
      "FiveMinMean": 252,
      "HourlyMean": 251,
      "DailyMean": 250,
      "WeeklyMean": 237,
      "MonthlyMean": 204,
      "BullishConfluence": 4,
      "BearishConfluence": 1,
      "SignalStrength": "STRONG_BULLISH",
      "VolumeConfirmation": "VOLUME_SUPPORTED",
      "PotentialProfit": 276100.0
    },
    {
      "ItemName": "Adamant arrowtips",
      "CurrentPrice": 218,
      "BuyLimit": 10000,
      "FiveMinMean": 131,
      "HourlyMean": 174,
      "DailyMean": 109,
      "WeeklyMean": 93,
      "MonthlyMean": 87,
      "BullishConfluence": 4,
      "BearishConfluence": 1,
      "SignalStrength": "STRONG_BULLISH",
      "VolumeConfirmation": "VOLUME_SUPPORTED",
      "PotentialProfit": 218000.0
    }
  ],
  "methodology": "VeryGranular_MultiTimeframeConfluence"
}