{
  "updated": "2025-09-03T05:35:44.487373+00:00",
  "items": [
    {
      "ItemName": "Arceuus library teleport (tablet)",
      "LowPrice": 1352,
      "AvgLow": 1608,
      "BuyLimit": 10000,
      "pctROI": 17.75
    },
    {
      "ItemName": "Dragon pickaxe",
      "LowPrice": 670000,
      "AvgLow": 731201,
      "BuyLimit": 40,
      "pctROI": 8.04
    },
    {
      "ItemName": "Aranea boots",
      "LowPrice": 3597581,
      "AvgLow": 3840295,
      "BuyLimit": 8,
      "pctROI": 5.68
    },
    {
      "ItemName": "Salve graveyard teleport (tablet)",
      "LowPrice": 2215,
      "AvgLow": 2365,
      "BuyLimit": 10000,
      "pctROI": 5.73
    },
    {
      "ItemName": "Zombie pirate key",
      "LowPrice": 10100,
      "AvgLow": 13657,
      "BuyLimit": 250,
      "pctROI": 33.87
    },
    {
      "ItemName": "Araxyte venom sack",
      "LowPrice": 1346,
      "AvgLow": 1429,
      "BuyLimit": 11000,
      "pctROI": 5.13
    },
    {
      "ItemName": "Raw pyre fox",
      "LowPrice": 56,
      "AvgLow": 79,
      "BuyLimit": 13000,
      "pctROI": 41.07
    }
  ],
  "methodology": "VeryGranular"
}