{
  "updated": "2025-12-23T16:00:37.606398+00:00",
  "items": [
    {
      "ItemName": "Blue moon chestplate",
      "LowPrice": 1025891,
      "AvgLow": 1301426,
      "BuyLimit": 15,
      "pctROI": 25.59
    },
    {
      "ItemName": "Pest control teleport",
      "LowPrice": 534,
      "AvgLow": 767,
      "BuyLimit": 10000,
      "pctROI": 42.32
    },
    {
      "ItemName": "Ruby bolts",
      "LowPrice": 204,
      "AvgLow": 343,
      "BuyLimit": 11000,
      "pctROI": 66.67
    },
    {
      "ItemName": "Zombie pirate key",
      "LowPrice": 7693,
      "AvgLow": 11086,
      "BuyLimit": 250,
      "pctROI": 42.68
    },
    {
      "ItemName": "Ahrim's hood",
      "LowPrice": 312289,
      "AvgLow": 355269,
      "BuyLimit": 15,
      "pctROI": 12.63
    },
    {
      "ItemName": "Grimy tarromin",
      "LowPrice": 179,
      "AvgLow": 206,
      "BuyLimit": 13000,
      "pctROI": 13.97
    },
    {
      "ItemName": "Maple seed",
      "LowPrice": 1467,
      "AvgLow": 2289,
      "BuyLimit": 200,
      "pctROI": 54.53
    },
    {
      "ItemName": "Adamantite ore",
      "LowPrice": 559,
      "AvgLow": 594,
      "BuyLimit": 4500,
      "pctROI": 5.37
    },
    {
      "ItemName": "Bandos cloak",
      "LowPrice": 1000,
      "AvgLow": 17489,
      "BuyLimit": 8,
      "pctROI": 1631.5
    }
  ],
  "methodology": "VeryGranular"
}