{
  "updated": "2025-08-28T04:00:34.837772+00:00",
  "items": [
    {
      "ItemName": "Dragon limbs",
      "LowPrice": 600000,
      "AvgLow": 1087871,
      "BuyLimit": 10000,
      "pctROI": 79.5
    },
    {
      "ItemName": "Divine super combat potion(2)",
      "LowPrice": 10600,
      "AvgLow": 12330,
      "BuyLimit": 2000,
      "pctROI": 15.16
    },
    {
      "ItemName": "Raw manta ray",
      "LowPrice": 2973,
      "AvgLow": 3147,
      "BuyLimit": 15000,
      "pctROI": 4.81
    },
    {
      "ItemName": "Granite boots",
      "LowPrice": 256111,
      "AvgLow": 288352,
      "BuyLimit": 70,
      "pctROI": 11.46
    },
    {
      "ItemName": "Ranging potion(1)",
      "LowPrice": 780,
      "AvgLow": 1331,
      "BuyLimit": 2000,
      "pctROI": 68.97
    },
    {
      "ItemName": "Verac's armour set",
      "LowPrice": 500000,
      "AvgLow": 602276,
      "BuyLimit": 8,
      "pctROI": 19.25
    },
    {
      "ItemName": "Anchovy pizza",
      "LowPrice": 483,
      "AvgLow": 532,
      "BuyLimit": 10000,
      "pctROI": 9.11
    }
  ],
  "methodology": "VeryGranular"
}