{
  "updated": "2025-07-13T17:40:32.507870+00:00",
  "items": [
    {
      "ItemName": "Cape of skulls",
      "LowPrice": 4312225,
      "AvgLow": 4591084,
      "BuyLimit": 8,
      "pctROI": 5.4
    },
    {
      "ItemName": "Barbarian teleport (tablet)",
      "LowPrice": 576,
      "AvgLow": 883,
      "BuyLimit": 10000,
      "pctROI": 51.91
    },
    {
      "ItemName": "Mystic robe top (dark)",
      "LowPrice": 55550,
      "AvgLow": 70753,
      "BuyLimit": 70,
      "pctROI": 26.1
    },
    {
      "ItemName": "Rune shield (h2)",
      "LowPrice": 31766,
      "AvgLow": 42628,
      "BuyLimit": 70,
      "pctROI": 32.85
    },
    {
      "ItemName": "Zamorakian hasta",
      "LowPrice": 1829362,
      "AvgLow": 1929601,
      "BuyLimit": 8,
      "pctROI": 4.42
    },
    {
      "ItemName": "Splitbark helm",
      "LowPrice": 2,
      "AvgLow": 7141,
      "BuyLimit": 70,
      "pctROI": 353400.0
    },
    {
      "ItemName": "Charge dragonstone jewellery scroll",
      "LowPrice": 100,
      "AvgLow": 143,
      "BuyLimit": 10000,
      "pctROI": 42.0
    },
    {
      "ItemName": "Raw swordfish",
      "LowPrice": 67,
      "AvgLow": 91,
      "BuyLimit": 15000,
      "pctROI": 35.82
    },
    {
      "ItemName": "Red spiders' eggs",
      "LowPrice": 290,
      "AvgLow": 305,
      "BuyLimit": 13000,
      "pctROI": 4.14
    },
    {
      "ItemName": "Guthix full helm",
      "LowPrice": 12000,
      "AvgLow": 25181,
      "BuyLimit": 8,
      "pctROI": 107.75
    }
  ],
  "methodology": "VeryGranular"
}