{
  "updated": "2025-11-27T21:35:37.953556+00:00",
  "items": [
    {
      "ItemName": "Revenant ether",
      "CurrentPrice": 172,
      "CurrentHigh": 175,
      "BuyLimit": 30000,
      "LowPriceVolume": "62215",
      "HighPriceVolume": "138015",
      "WeeklyLowVolume": "12052313",
      "WeeklyHighVolume": "24921169",
      "VolumeImbalanceRatio": 12443.0,
      "VolumePattern": "STRONG_DISTRIBUTION",
      "VolumeSurge": "NORMAL_VOLUME",
      "SmartMoneySignal": "NO_SMART_MONEY_SIGNAL",
      "AccumulationProfit": 0
    },
    {
      "ItemName": "Blood rune",
      "CurrentPrice": 203,
      "CurrentHigh": 207,
      "BuyLimit": 25000,
      "LowPriceVolume": "53665",
      "HighPriceVolume": "105537",
      "WeeklyLowVolume": "9553621",
      "WeeklyHighVolume": "22001752",
      "VolumeImbalanceRatio": 10733.0,
      "VolumePattern": "MODERATE_DISTRIBUTION",
      "VolumeSurge": "NORMAL_VOLUME",
      "SmartMoneySignal": "NO_SMART_MONEY_SIGNAL",
      "AccumulationProfit": 0
    },
    {
      "ItemName": "Coal",
      "CurrentPrice": 227,
      "CurrentHigh": 229,
      "BuyLimit": 13000,
      "LowPriceVolume": "37636",
      "HighPriceVolume": "43947",
      "WeeklyLowVolume": "7623106",
      "WeeklyHighVolume": "8243275",
      "VolumeImbalanceRatio": 7527.2,
      "VolumePattern": "BALANCED",
      "VolumeSurge": "NORMAL_VOLUME",
      "SmartMoneySignal": "NO_SMART_MONEY_SIGNAL",
      "AccumulationProfit": 0
    },
    {
      "ItemName": "Rune arrow",
      "CurrentPrice": 258,
      "CurrentHigh": 262,
      "BuyLimit": 11000,
      "LowPriceVolume": "28732",
      "HighPriceVolume": "27602",
      "WeeklyLowVolume": "5947652",
      "WeeklyHighVolume": "5540872",
      "VolumeImbalanceRatio": 5746.4,
      "VolumePattern": "BALANCED",
      "VolumeSurge": "NORMAL_VOLUME",
      "SmartMoneySignal": "NO_SMART_MONEY_SIGNAL",
      "AccumulationProfit": 0
    },
    {
      "ItemName": "Amethyst arrowtips",
      "CurrentPrice": 276,
      "CurrentHigh": 289,
      "BuyLimit": 10000,
      "LowPriceVolume": "25308",
      "HighPriceVolume": "28607",
      "WeeklyLowVolume": "1747419",
      "WeeklyHighVolume": "3127200",
      "VolumeImbalanceRatio": 5061.6,
      "VolumePattern": "BALANCED",
      "VolumeSurge": "NORMAL_VOLUME",
      "SmartMoneySignal": "NO_SMART_MONEY_SIGNAL",
      "AccumulationProfit": 0
    },
    {
      "ItemName": "Steel cannonball",
      "CurrentPrice": 230,
      "CurrentHigh": 241,
      "BuyLimit": 11000,
      "LowPriceVolume": "21985",
      "HighPriceVolume": "110697",
      "WeeklyLowVolume": "4690386",
      "WeeklyHighVolume": "24572315",
      "VolumeImbalanceRatio": 4397.0,
      "VolumePattern": "STRONG_DISTRIBUTION",
      "VolumeSurge": "NORMAL_VOLUME",
      "SmartMoneySignal": "NO_SMART_MONEY_SIGNAL",
      "AccumulationProfit": 0
    },
    {
      "ItemName": "Broad arrowheads",
      "CurrentPrice": 52,
      "CurrentHigh": 54,
      "BuyLimit": 7000,
      "LowPriceVolume": "21955",
      "HighPriceVolume": "4902",
      "WeeklyLowVolume": "89808",
      "WeeklyHighVolume": "64848",
      "VolumeImbalanceRatio": 4391.0,
      "VolumePattern": "STRONG_ACCUMULATION",
      "VolumeSurge": "NORMAL_VOLUME",
      "SmartMoneySignal": "NO_SMART_MONEY_SIGNAL",
      "AccumulationProfit": 14000.0
    },
    {
      "ItemName": "Gold ore",
      "CurrentPrice": 117,
      "CurrentHigh": 121,
      "BuyLimit": 30000,
      "LowPriceVolume": "21418",
      "HighPriceVolume": "13246",
      "WeeklyLowVolume": "4001253",
      "WeeklyHighVolume": "3580739",
      "VolumeImbalanceRatio": 4283.6,
      "VolumePattern": "MODERATE_ACCUMULATION",
      "VolumeSurge": "NORMAL_VOLUME",
      "SmartMoneySignal": "NO_SMART_MONEY_SIGNAL",
      "AccumulationProfit": 175500.0
    },
    {
      "ItemName": "Wrath rune",
      "CurrentPrice": 302,
      "CurrentHigh": 307,
      "BuyLimit": 25000,
      "LowPriceVolume": "20819",
      "HighPriceVolume": "49478",
      "WeeklyLowVolume": "2858941",
      "WeeklyHighVolume": "7524563",
      "VolumeImbalanceRatio": 4163.8,
      "VolumePattern": "STRONG_DISTRIBUTION",
      "VolumeSurge": "NORMAL_VOLUME",
      "SmartMoneySignal": "NO_SMART_MONEY_SIGNAL",
      "AccumulationProfit": 0
    },
    {
      "ItemName": "Sunfire rune",
      "CurrentPrice": 106,
      "CurrentHigh": 110,
      "BuyLimit": 18000,
      "LowPriceVolume": "19597",
      "HighPriceVolume": "21434",
      "WeeklyLowVolume": "362282",
      "WeeklyHighVolume": "1226818",
      "VolumeImbalanceRatio": 3919.4,
      "VolumePattern": "BALANCED",
      "VolumeSurge": "NORMAL_VOLUME",
      "SmartMoneySignal": "NO_SMART_MONEY_SIGNAL",
      "AccumulationProfit": 0
    },
    {
      "ItemName": "Adamant dart",
      "CurrentPrice": 56,
      "CurrentHigh": 57,
      "BuyLimit": 11000,
      "LowPriceVolume": "19485",
      "HighPriceVolume": "29848",
      "WeeklyLowVolume": "2660834",
      "WeeklyHighVolume": "5680498",
      "VolumeImbalanceRatio": 3897.0,
      "VolumePattern": "MODERATE_DISTRIBUTION",
      "VolumeSurge": "NORMAL_VOLUME",
      "SmartMoneySignal": "NO_SMART_MONEY_SIGNAL",
      "AccumulationProfit": 0
    },
    {
      "ItemName": "Law rune",
      "CurrentPrice": 118,
      "CurrentHigh": 120,
      "BuyLimit": 18000,
      "LowPriceVolume": "16485",
      "HighPriceVolume": "35294",
      "WeeklyLowVolume": "3663575",
      "WeeklyHighVolume": "8550775",
      "VolumeImbalanceRatio": 3297.0,
      "VolumePattern": "STRONG_DISTRIBUTION",
      "VolumeSurge": "NORMAL_VOLUME",
      "SmartMoneySignal": "NO_SMART_MONEY_SIGNAL",
      "AccumulationProfit": 0
    },
    {
      "ItemName": "Adamant arrow",
      "CurrentPrice": 78,
      "CurrentHigh": 84,
      "BuyLimit": 11000,
      "LowPriceVolume": "16453",
      "HighPriceVolume": "18611",
      "WeeklyLowVolume": "2684251",
      "WeeklyHighVolume": "3115444",
      "VolumeImbalanceRatio": 3290.6,
      "VolumePattern": "BALANCED",
      "VolumeSurge": "NORMAL_VOLUME",
      "SmartMoneySignal": "NO_SMART_MONEY_SIGNAL",
      "AccumulationProfit": 0
    },
    {
      "ItemName": "Amethyst arrow",
      "CurrentPrice": 314,
      "CurrentHigh": 324,
      "BuyLimit": 11000,
      "LowPriceVolume": "15310",
      "HighPriceVolume": "31908",
      "WeeklyLowVolume": "3311037",
      "WeeklyHighVolume": "5815383",
      "VolumeImbalanceRatio": 3062.0,
      "VolumePattern": "STRONG_DISTRIBUTION",
      "VolumeSurge": "NORMAL_VOLUME",
      "SmartMoneySignal": "NO_SMART_MONEY_SIGNAL",
      "AccumulationProfit": 0
    },
    {
      "ItemName": "Mahogany logs",
      "CurrentPrice": 283,
      "CurrentHigh": 285,
      "BuyLimit": 11000,
      "LowPriceVolume": "15014",
      "HighPriceVolume": "10493",
      "WeeklyLowVolume": "3001476",
      "WeeklyHighVolume": "2421039",
      "VolumeImbalanceRatio": 3002.8,
      "VolumePattern": "BALANCED",
      "VolumeSurge": "NORMAL_VOLUME",
      "SmartMoneySignal": "NO_SMART_MONEY_SIGNAL",
      "AccumulationProfit": 0
    },
    {
      "ItemName": "Gold bar",
      "CurrentPrice": 109,
      "CurrentHigh": 112,
      "BuyLimit": 10000,
      "LowPriceVolume": "12673",
      "HighPriceVolume": "14563",
      "WeeklyLowVolume": "3654879",
      "WeeklyHighVolume": "2853236",
      "VolumeImbalanceRatio": 2534.6,
      "VolumePattern": "BALANCED",
      "VolumeSurge": "NORMAL_VOLUME",
      "SmartMoneySignal": "NO_SMART_MONEY_SIGNAL",
      "AccumulationProfit": 0
    },
    {
      "ItemName": "Astral rune",
      "CurrentPrice": 66,
      "CurrentHigh": 69,
      "BuyLimit": 25000,
      "LowPriceVolume": "12136",
      "HighPriceVolume": "39587",
      "WeeklyLowVolume": "1677893",
      "WeeklyHighVolume": "7156144",
      "VolumeImbalanceRatio": 2427.2,
      "VolumePattern": "STRONG_DISTRIBUTION",
      "VolumeSurge": "NORMAL_VOLUME",
      "SmartMoneySignal": "NO_SMART_MONEY_SIGNAL",
      "AccumulationProfit": 0
    },
    {
      "ItemName": "Mithril cannonball",
      "CurrentPrice": 520,
      "CurrentHigh": 524,
      "BuyLimit": 11000,
      "LowPriceVolume": "11975",
      "HighPriceVolume": "15387",
      "WeeklyLowVolume": "2536144",
      "WeeklyHighVolume": "3657709",
      "VolumeImbalanceRatio": 2395.0,
      "VolumePattern": "BALANCED",
      "VolumeSurge": "NORMAL_VOLUME",
      "SmartMoneySignal": "NO_SMART_MONEY_SIGNAL",
      "AccumulationProfit": 0
    },
    {
      "ItemName": "Amethyst dart tip",
      "CurrentPrice": 515,
      "CurrentHigh": 525,
      "BuyLimit": 11000,
      "LowPriceVolume": "11910",
      "HighPriceVolume": "15803",
      "WeeklyLowVolume": "1086490",
      "WeeklyHighVolume": "1559840",
      "VolumeImbalanceRatio": 2382.0,
      "VolumePattern": "BALANCED",
      "VolumeSurge": "NORMAL_VOLUME",
      "SmartMoneySignal": "NO_SMART_MONEY_SIGNAL",
      "AccumulationProfit": 0
    },
    {
      "ItemName": "Cosmic rune",
      "CurrentPrice": 113,
      "CurrentHigh": 114,
      "BuyLimit": 18000,
      "LowPriceVolume": "11566",
      "HighPriceVolume": "28967",
      "WeeklyLowVolume": "2466819",
      "WeeklyHighVolume": "5365408",
      "VolumeImbalanceRatio": 2313.2,
      "VolumePattern": "STRONG_DISTRIBUTION",
      "VolumeSurge": "NORMAL_VOLUME",
      "SmartMoneySignal": "NO_SMART_MONEY_SIGNAL",
      "AccumulationProfit": 0
    },
    {
      "ItemName": "Adamant cannonball",
      "CurrentPrice": 785,
      "CurrentHigh": 798,
      "BuyLimit": 11000,
      "LowPriceVolume": "11077",
      "HighPriceVolume": "16573",
      "WeeklyLowVolume": "1782898",
      "WeeklyHighVolume": "3065225",
      "VolumeImbalanceRatio": 2215.4,
      "VolumePattern": "BALANCED",
      "VolumeSurge": "NORMAL_VOLUME",
      "SmartMoneySignal": "NO_SMART_MONEY_SIGNAL",
      "AccumulationProfit": 0
    },
    {
      "ItemName": "Demon tear",
      "CurrentPrice": 195,
      "CurrentHigh": 206,
      "BuyLimit": 13000,
      "LowPriceVolume": "10897",
      "HighPriceVolume": "39410",
      "WeeklyLowVolume": "1934688",
      "WeeklyHighVolume": "7056956",
      "VolumeImbalanceRatio": 2179.4,
      "VolumePattern": "STRONG_DISTRIBUTION",
      "VolumeSurge": "NORMAL_VOLUME",
      "SmartMoneySignal": "NO_SMART_MONEY_SIGNAL",
      "AccumulationProfit": 0
    },
    {
      "ItemName": "Yew logs",
      "CurrentPrice": 177,
      "CurrentHigh": 177,
      "BuyLimit": 12000,
      "LowPriceVolume": "10873",
      "HighPriceVolume": "11378",
      "WeeklyLowVolume": "1826315",
      "WeeklyHighVolume": "2134901",
      "VolumeImbalanceRatio": 2174.6,
      "VolumePattern": "BALANCED",
      "VolumeSurge": "NORMAL_VOLUME",
      "SmartMoneySignal": "NO_SMART_MONEY_SIGNAL",
      "AccumulationProfit": 0
    },
    {
      "ItemName": "Mahogany plank",
      "CurrentPrice": 1951,
      "CurrentHigh": 2003,
      "BuyLimit": 13000,
      "LowPriceVolume": "10704",
      "HighPriceVolume": "21882",
      "WeeklyLowVolume": "2810470",
      "WeeklyHighVolume": "4574216",
      "VolumeImbalanceRatio": 2140.8,
      "VolumePattern": "STRONG_DISTRIBUTION",
      "VolumeSurge": "NORMAL_VOLUME",
      "SmartMoneySignal": "NO_SMART_MONEY_SIGNAL",
      "AccumulationProfit": 0
    },
    {
      "ItemName": "Adamant dart tip",
      "CurrentPrice": 221,
      "CurrentHigh": 222,
      "BuyLimit": 20000,
      "LowPriceVolume": "9934",
      "HighPriceVolume": "21327",
      "WeeklyLowVolume": "1819394",
      "WeeklyHighVolume": "2868226",
      "VolumeImbalanceRatio": 1986.8,
      "VolumePattern": "STRONG_DISTRIBUTION",
      "VolumeSurge": "NORMAL_VOLUME",
      "SmartMoneySignal": "NO_SMART_MONEY_SIGNAL",
      "AccumulationProfit": 0
    },
    {
      "ItemName": "Grapes",
      "CurrentPrice": 75,
      "CurrentHigh": 76,
      "BuyLimit": 20000,
      "LowPriceVolume": "9930",
      "HighPriceVolume": "12641",
      "WeeklyLowVolume": "2335796",
      "WeeklyHighVolume": "2038494",
      "VolumeImbalanceRatio": 1986.0,
      "VolumePattern": "BALANCED",
      "VolumeSurge": "NORMAL_VOLUME",
      "SmartMoneySignal": "NO_SMART_MONEY_SIGNAL",
      "AccumulationProfit": 0
    },
    {
      "ItemName": "Oak plank",
      "CurrentPrice": 353,
      "CurrentHigh": 357,
      "BuyLimit": 13000,
      "LowPriceVolume": "9558",
      "HighPriceVolume": "13394",
      "WeeklyLowVolume": "2208577",
      "WeeklyHighVolume": "3782542",
      "VolumeImbalanceRatio": 1911.6,
      "VolumePattern": "BALANCED",
      "VolumeSurge": "NORMAL_VOLUME",
      "SmartMoneySignal": "NO_SMART_MONEY_SIGNAL",
      "AccumulationProfit": 0
    },
    {
      "ItemName": "Adamantite nails",
      "CurrentPrice": 163,
      "CurrentHigh": 172,
      "BuyLimit": 13000,
      "LowPriceVolume": "9263",
      "HighPriceVolume": "24294",
      "WeeklyLowVolume": "1511726",
      "WeeklyHighVolume": "5421375",
      "VolumeImbalanceRatio": 1852.6,
      "VolumePattern": "STRONG_DISTRIBUTION",
      "VolumeSurge": "NORMAL_VOLUME",
      "SmartMoneySignal": "NO_SMART_MONEY_SIGNAL",
      "AccumulationProfit": 0
    },
    {
      "ItemName": "Mithril nails",
      "CurrentPrice": 98,
      "CurrentHigh": 101,
      "BuyLimit": 13000,
      "LowPriceVolume": "9061",
      "HighPriceVolume": "48524",
      "WeeklyLowVolume": "3367478",
      "WeeklyHighVolume": "13066918",
      "VolumeImbalanceRatio": 1812.2,
      "VolumePattern": "STRONG_DISTRIBUTION",
      "VolumeSurge": "NORMAL_VOLUME",
      "SmartMoneySignal": "NO_SMART_MONEY_SIGNAL",
      "AccumulationProfit": 0
    },
    {
      "ItemName": "Steel bar",
      "CurrentPrice": 599,
      "CurrentHigh": 611,
      "BuyLimit": 10000,
      "LowPriceVolume": "9019",
      "HighPriceVolume": "13502",
      "WeeklyLowVolume": "1888915",
      "WeeklyHighVolume": "3924850",
      "VolumeImbalanceRatio": 1803.8,
      "VolumePattern": "BALANCED",
      "VolumeSurge": "NORMAL_VOLUME",
      "SmartMoneySignal": "NO_SMART_MONEY_SIGNAL",
      "AccumulationProfit": 0
    },
    {
      "ItemName": "Amethyst dart",
      "CurrentPrice": 360,
      "CurrentHigh": 373,
      "BuyLimit": 11000,
      "LowPriceVolume": "8921",
      "HighPriceVolume": "15585",
      "WeeklyLowVolume": "2168982",
      "WeeklyHighVolume": "2761230",
      "VolumeImbalanceRatio": 1784.2,
      "VolumePattern": "MODERATE_DISTRIBUTION",
      "VolumeSurge": "NORMAL_VOLUME",
      "SmartMoneySignal": "NO_SMART_MONEY_SIGNAL",
      "AccumulationProfit": 0
    },
    {
      "ItemName": "Mithril ore",
      "CurrentPrice": 124,
      "CurrentHigh": 129,
      "BuyLimit": 13000,
      "LowPriceVolume": "8878",
      "HighPriceVolume": "4818",
      "WeeklyLowVolume": "1586481",
      "WeeklyHighVolume": "959409",
      "VolumeImbalanceRatio": 1775.6,
      "VolumePattern": "MODERATE_ACCUMULATION",
      "VolumeSurge": "NORMAL_VOLUME",
      "SmartMoneySignal": "NO_SMART_MONEY_SIGNAL",
      "AccumulationProfit": 80600.0
    },
    {
      "ItemName": "Aether rune",
      "CurrentPrice": 600,
      "CurrentHigh": 617,
      "BuyLimit": 25000,
      "LowPriceVolume": "8743",
      "HighPriceVolume": "10499",
      "WeeklyLowVolume": "477449",
      "WeeklyHighVolume": "1899949",
      "VolumeImbalanceRatio": 1748.6,
      "VolumePattern": "BALANCED",
      "VolumeSurge": "NORMAL_VOLUME",
      "SmartMoneySignal": "NO_SMART_MONEY_SIGNAL",
      "AccumulationProfit": 0
    },
    {
      "ItemName": "Mithril dart tip",
      "CurrentPrice": 122,
      "CurrentHigh": 128,
      "BuyLimit": 20000,
      "LowPriceVolume": "8099",
      "HighPriceVolume": "12239",
      "WeeklyLowVolume": "1479183",
      "WeeklyHighVolume": "2137047",
      "VolumeImbalanceRatio": 1619.8,
      "VolumePattern": "MODERATE_DISTRIBUTION",
      "VolumeSurge": "NORMAL_VOLUME",
      "SmartMoneySignal": "NO_SMART_MONEY_SIGNAL",
      "AccumulationProfit": 0
    },
    {
      "ItemName": "Pat of butter",
      "CurrentPrice": 34,
      "CurrentHigh": 67,
      "BuyLimit": 11000,
      "LowPriceVolume": "7916",
      "HighPriceVolume": "1475",
      "WeeklyLowVolume": "81238",
      "WeeklyHighVolume": "85029",
      "VolumeImbalanceRatio": 1583.2,
      "VolumePattern": "STRONG_ACCUMULATION",
      "VolumeSurge": "NORMAL_VOLUME",
      "SmartMoneySignal": "NO_SMART_MONEY_SIGNAL",
      "AccumulationProfit": 363000.0
    },
    {
      "ItemName": "Sunfire splinters",
      "CurrentPrice": 146,
      "CurrentHigh": 150,
      "BuyLimit": 30000,
      "LowPriceVolume": "7363",
      "HighPriceVolume": "28084",
      "WeeklyLowVolume": "1288832",
      "WeeklyHighVolume": "4289713",
      "VolumeImbalanceRatio": 1472.6,
      "VolumePattern": "STRONG_DISTRIBUTION",
      "VolumeSurge": "NORMAL_VOLUME",
      "SmartMoneySignal": "NO_SMART_MONEY_SIGNAL",
      "AccumulationProfit": 0
    },
    {
      "ItemName": "Unfinished broad bolts",
      "CurrentPrice": 60,
      "CurrentHigh": 65,
      "BuyLimit": 7000,
      "LowPriceVolume": "7071",
      "HighPriceVolume": "3209",
      "WeeklyLowVolume": "52415",
      "WeeklyHighVolume": "37577",
      "VolumeImbalanceRatio": 1414.2,
      "VolumePattern": "STRONG_ACCUMULATION",
      "VolumeSurge": "NORMAL_VOLUME",
      "SmartMoneySignal": "NO_SMART_MONEY_SIGNAL",
      "AccumulationProfit": 35000.0
    },
    {
      "ItemName": "Diamond bolts (e)",
      "CurrentPrice": 240,
      "CurrentHigh": 241,
      "BuyLimit": 11000,
      "LowPriceVolume": "7048",
      "HighPriceVolume": "4674",
      "WeeklyLowVolume": "1071353",
      "WeeklyHighVolume": "974992",
      "VolumeImbalanceRatio": 1409.6,
      "VolumePattern": "MODERATE_ACCUMULATION",
      "VolumeSurge": "NORMAL_VOLUME",
      "SmartMoneySignal": "NO_SMART_MONEY_SIGNAL",
      "AccumulationProfit": 132000.0
    },
    {
      "ItemName": "Steel nails",
      "CurrentPrice": 42,
      "CurrentHigh": 42,
      "BuyLimit": 13000,
      "LowPriceVolume": "6934",
      "HighPriceVolume": "21356",
      "WeeklyLowVolume": "1879042",
      "WeeklyHighVolume": "6839244",
      "VolumeImbalanceRatio": 1386.8,
      "VolumePattern": "STRONG_DISTRIBUTION",
      "VolumeSurge": "NORMAL_VOLUME",
      "SmartMoneySignal": "NO_SMART_MONEY_SIGNAL",
      "AccumulationProfit": 0
    },
    {
      "ItemName": "Forester's ration",
      "CurrentPrice": 28,
      "CurrentHigh": 34,
      "BuyLimit": 6000,
      "LowPriceVolume": "6346",
      "HighPriceVolume": "10691",
      "WeeklyLowVolume": "177250",
      "WeeklyHighVolume": "1350904",
      "VolumeImbalanceRatio": 1269.2,
      "VolumePattern": "MODERATE_DISTRIBUTION",
      "VolumeSurge": "NORMAL_VOLUME",
      "SmartMoneySignal": "NO_SMART_MONEY_SIGNAL",
      "AccumulationProfit": 0
    },
    {
      "ItemName": "Silver ore",
      "CurrentPrice": 51,
      "CurrentHigh": 52,
      "BuyLimit": 13000,
      "LowPriceVolume": "6313",
      "HighPriceVolume": "3091",
      "WeeklyLowVolume": "1020969",
      "WeeklyHighVolume": "358499",
      "VolumeImbalanceRatio": 1262.6,
      "VolumePattern": "STRONG_ACCUMULATION",
      "VolumeSurge": "NORMAL_VOLUME",
      "SmartMoneySignal": "NO_SMART_MONEY_SIGNAL",
      "AccumulationProfit": 13000.0
    },
    {
      "ItemName": "Rune cannonball",
      "CurrentPrice": 2116,
      "CurrentHigh": 2176,
      "BuyLimit": 11000,
      "LowPriceVolume": "6279",
      "HighPriceVolume": "3182",
      "WeeklyLowVolume": "898739",
      "WeeklyHighVolume": "441235",
      "VolumeImbalanceRatio": 1255.8,
      "VolumePattern": "MODERATE_ACCUMULATION",
      "VolumeSurge": "NORMAL_VOLUME",
      "SmartMoneySignal": "NO_SMART_MONEY_SIGNAL",
      "AccumulationProfit": 1163800.0
    },
    {
      "ItemName": "Moonlight antelope fur",
      "CurrentPrice": 275,
      "CurrentHigh": 303,
      "BuyLimit": 18000,
      "LowPriceVolume": "6267",
      "HighPriceVolume": "3279",
      "WeeklyLowVolume": "49500",
      "WeeklyHighVolume": "36155",
      "VolumeImbalanceRatio": 1253.4,
      "VolumePattern": "MODERATE_ACCUMULATION",
      "VolumeSurge": "NORMAL_VOLUME",
      "SmartMoneySignal": "NO_SMART_MONEY_SIGNAL",
      "AccumulationProfit": 247500.0
    },
    {
      "ItemName": "Aether catalyst",
      "CurrentPrice": 179,
      "CurrentHigh": 181,
      "BuyLimit": 25000,
      "LowPriceVolume": "5768",
      "HighPriceVolume": "4624",
      "WeeklyLowVolume": "1047467",
      "WeeklyHighVolume": "521555",
      "VolumeImbalanceRatio": 1153.6,
      "VolumePattern": "BALANCED",
      "VolumeSurge": "NORMAL_VOLUME",
      "SmartMoneySignal": "NO_SMART_MONEY_SIGNAL",
      "AccumulationProfit": 0
    },
    {
      "ItemName": "Blighted ancient ice sack",
      "CurrentPrice": 221,
      "CurrentHigh": 224,
      "BuyLimit": 15000,
      "LowPriceVolume": "5527",
      "HighPriceVolume": "12182",
      "WeeklyLowVolume": "1016450",
      "WeeklyHighVolume": "1985143",
      "VolumeImbalanceRatio": 1105.4,
      "VolumePattern": "STRONG_DISTRIBUTION",
      "VolumeSurge": "NORMAL_VOLUME",
      "SmartMoneySignal": "NO_SMART_MONEY_SIGNAL",
      "AccumulationProfit": 0
    },
    {
      "ItemName": "Iron cannonball",
      "CurrentPrice": 40,
      "CurrentHigh": 40,
      "BuyLimit": 11000,
      "LowPriceVolume": "5314",
      "HighPriceVolume": "17344",
      "WeeklyLowVolume": "2352438",
      "WeeklyHighVolume": "5329943",
      "VolumeImbalanceRatio": 1062.8,
      "VolumePattern": "STRONG_DISTRIBUTION",
      "VolumeSurge": "NORMAL_VOLUME",
      "SmartMoneySignal": "NO_SMART_MONEY_SIGNAL",
      "AccumulationProfit": 0
    },
    {
      "ItemName": "Shark",
      "CurrentPrice": 568,
      "CurrentHigh": 592,
      "BuyLimit": 10000,
      "LowPriceVolume": "5197",
      "HighPriceVolume": "10941",
      "WeeklyLowVolume": "1095180",
      "WeeklyHighVolume": "1987561",
      "VolumeImbalanceRatio": 1039.4,
      "VolumePattern": "STRONG_DISTRIBUTION",
      "VolumeSurge": "NORMAL_VOLUME",
      "SmartMoneySignal": "NO_SMART_MONEY_SIGNAL",
      "AccumulationProfit": 0
    },
    {
      "ItemName": "Iron ore",
      "CurrentPrice": 118,
      "CurrentHigh": 124,
      "BuyLimit": 13000,
      "LowPriceVolume": "5077",
      "HighPriceVolume": "11836",
      "WeeklyLowVolume": "1409242",
      "WeeklyHighVolume": "2508526",
      "VolumeImbalanceRatio": 1015.4,
      "VolumePattern": "STRONG_DISTRIBUTION",
      "VolumeSurge": "NORMAL_VOLUME",
      "SmartMoneySignal": "NO_SMART_MONEY_SIGNAL",
      "AccumulationProfit": 0
    },
    {
      "ItemName": "Plank",
      "CurrentPrice": 195,
      "CurrentHigh": 200,
      "BuyLimit": 13000,
      "LowPriceVolume": "4864",
      "HighPriceVolume": "3084",
      "WeeklyLowVolume": "1150552",
      "WeeklyHighVolume": "1094123",
      "VolumeImbalanceRatio": 972.8,
      "VolumePattern": "MODERATE_ACCUMULATION",
      "VolumeSurge": "NORMAL_VOLUME",
      "SmartMoneySignal": "NO_SMART_MONEY_SIGNAL",
      "AccumulationProfit": 126750.0
    },
    {
      "ItemName": "Magic longbow (u)",
      "CurrentPrice": 1111,
      "CurrentHigh": 1100,
      "BuyLimit": 10000,
      "LowPriceVolume": "4826",
      "HighPriceVolume": "2782",
      "WeeklyLowVolume": "609688",
      "WeeklyHighVolume": "503309",
      "VolumeImbalanceRatio": 965.2,
      "VolumePattern": "MODERATE_ACCUMULATION",
      "VolumeSurge": "NORMAL_VOLUME",
      "SmartMoneySignal": "NO_SMART_MONEY_SIGNAL",
      "AccumulationProfit": 555500.0
    }
  ],
  "methodology": "VeryGranular_VolumeProfile"
}